setup.py
bin/goverlap
go_overlap/__init__.py
go_overlap/main.py
go_overlap/version.py
go_overlap/compute_set_overlaps/__init__.py
go_overlap/compute_set_overlaps/set_overlaps.py
go_overlap/create_term_subtree_gene_matrix/__init__.py
go_overlap/create_term_subtree_gene_matrix/term_subtree_gene_matrix.py
go_overlap/gene_to_terms/__init__.py
go_overlap/gene_to_terms/terms_to_genes.py
go_overlap/go/__init__.py
go_overlap/go/terms_to_annotation.py
go_overlap/go_hierarchy/__init__.py
go_overlap/go_hierarchy/compute_parent_offspring_maps.py
go_overlap/prepare_input_lists/__init__.py
go_overlap/prepare_input_lists/lists_to_bool_vectors.py
go_overlap/statistics/__init__.py
go_overlap/statistics/create_gene_list_overlap_df.py
go_overlap/statistics/go_experiment_overlap.py
go_overlap/statistics/lap_ppv.py
go_overlap/statistics/set_arithmetic.py
go_overlap/statistics/stats.py
go_overlap/utils/__init__.py
go_overlap/utils/helper_functions.py
goverlap.egg-info/PKG-INFO
goverlap.egg-info/SOURCES.txt
goverlap.egg-info/dependency_links.txt
goverlap.egg-info/requires.txt
goverlap.egg-info/top_level.txt