Metadata-Version: 1.1
Name: goverlap
Version: 0.0.5
Summary: Powerful ontology term enrichment analyzer for the command line
Home-page: http://github.com/endrebak/goverlap
Author: Endre Bakken Stovner
Author-email: endrebak@stud.ntnu.no
License: ['MIT']
Keywords: Gene Ontology,Term enrichment
Platform: UNKNOWN
Classifier: Programming Language :: Python :: 2.7
Classifier: Programming Language :: Python :: 3
Classifier: Development Status :: 2 - Pre-Alpha
Classifier: Environment :: Other Environment
Classifier: Intended Audience :: Developers
Classifier: Intended Audience :: Science/Research
Classifier: License :: OSI Approved :: GNU General Public License v3 (GPLv3)
Classifier: Operating System :: POSIX :: Linux
Classifier: Operating System :: MacOS :: MacOS X
Classifier: Topic :: Scientific/Engineering
Classifier: Topic :: Scientific/Engineering :: Interface Engine/Protocol Translator
Classifier: Topic :: Software Development :: Libraries :: Python Modules
